README.rst
searchgrid.py
setup.cfg
setup.py
searchgrid.egg-info/PKG-INFO
searchgrid.egg-info/SOURCES.txt
searchgrid.egg-info/dependency_links.txt
searchgrid.egg-info/requires.txt
searchgrid.egg-info/top_level.txt