Metadata-Version: 1.1
Name: searchgrid
Version: 0.2.0
Summary: Helpers for building parameter grids for scikit-learn grid search
Home-page: https://searchgrid.readthedocs.io
Author: Joel Nothman
Author-email: joel.nothman@gmail.com
License: BSD 3-Clause License
Platform: UNKNOWN
Classifier: Programming Language :: Python :: 2
Classifier: Programming Language :: Python :: 2.7
Classifier: Programming Language :: Python :: 3
Classifier: Programming Language :: Python :: 3.5
Classifier: Programming Language :: Python :: 3.6
